offline_results/__init__.py
offline_results/api/__init__.py
offline_results/api/homepage_cluster_category.py
offline_results/api/homepage_recommendation.py
offline_results/api/ranking.py
offline_results/clustering/__init__.py
offline_results/clustering/centroids_generator.py
offline_results/clustering/cluster_feature_generator.py
offline_results/clustering/cluster_generator.py
offline_results/clustering/clustering_utils.py
offline_results/clustering/config.py
offline_results/clustering/inter_centroid_distance.py
offline_results/clustering/main.py
offline_results/clustering/mean_user_from_cluster.py
offline_results/clustering/reclustering.py
offline_results/clustering/utils.py
offline_results/common/__init__.py
offline_results/common/config.py
offline_results/common/constants.py
offline_results/common/convert_time_zone.py
offline_results/common/read_write_from_s3.py
offline_results/controller/HICR_content_based_filtering_controller.py
offline_results/controller/HICR_item_to_item_filtering_controller.py
offline_results/controller/HICR_preference_and_recency_based_controller.py
offline_results/controller/HICR_user_to_user_filtering_controller.py
offline_results/controller/__init__.py
offline_results/controller/homepage_id_recommendation_controller.py
offline_results/interface/__init__.py
offline_results/interface/recommendation_iface.py
offline_results/main.py
offline_results/preferences/__init__.py
offline_results/preferences/generate_preferences.py
offline_results/preferences/relationship_extractor.py
offline_results/preferences/viewtime_preferences.py
offline_results/recommendation/__init__.py
offline_results/recommendation/homepage_cluster_category/__init__.py
offline_results/recommendation/homepage_cluster_category/config.py
offline_results/recommendation/homepage_cluster_category/homepage_ids_contents_recommendation/__init__.py
offline_results/recommendation/homepage_cluster_category/hompage_id_recommendation/__init__.py
offline_rce_results_module-0.9.22.dist-info/WHEEL
offline_rce_results_module-0.9.22.dist-info/METADATA
offline_rce_results_module-0.9.22.dist-info/RECORD
