Metadata-Version: 2.1
Name: offline-rce-results-module
Version: 0.9.22
Summary: 
License: MIT
Author: AIML Team
Requires-Python: >=3.8,<3.11
Classifier: License :: OSI Approved :: MIT License
Classifier: Programming Language :: Python :: 3
Classifier: Programming Language :: Python :: 3.8
Classifier: Programming Language :: Python :: 3.9
Classifier: Programming Language :: Python :: 3.10
Classifier: Programming Language :: Python :: 3
Classifier: Programming Language :: Python :: 3.10
Classifier: Programming Language :: Python :: 3.11
Classifier: Programming Language :: Python :: 3.7
Classifier: Programming Language :: Python :: 3.8
Classifier: Programming Language :: Python :: 3.9
Requires-Dist: Flask (>=2.2.0,<3.0.0)
Requires-Dist: Sastrawi (>=1.0.1,<2.0.0)
Requires-Dist: boto3 (>=1.20.50,<2.0.0)
Requires-Dist: cachetools (>=5.2.0,<6.0.0)
Requires-Dist: cython (>=0.29.32,<0.30.0)
Requires-Dist: dask[distributed] (>=2022.12.0,<2023.0.0)
Requires-Dist: graphdb-module (>=0.12.16)
Requires-Dist: hijri-converter (>=2.2.4,<3.0.0)
Requires-Dist: joblib (>=1.2.0,<2.0.0)
Requires-Dist: networkx (>=2.8.5,<3.0.0)
Requires-Dist: nltk (>=3.7,<4.0)
Requires-Dist: numpy (>=1.23.5,<2.0.0)
Requires-Dist: pandas (>=1.4.0,<2.0.0)
Requires-Dist: pathlib (>=1.0.1,<2.0.0)
Requires-Dist: redis (>=4.1.2,<5.0.0)
Requires-Dist: scikit-learn (>=1.0.2,<2.0.0)
Requires-Dist: scikit-surprise (==1.1.3)
Requires-Dist: tensorflow (>=2.10.0,<3.0.0)
Requires-Dist: tqdm (>=4.63.0,<5.0.0)
Requires-Dist: yellowbrick (==1.5)
